{
    "title": "Open Demo Account | IC Markets",
    "meta": "Icmarkets provides best online forex trading platform. Our popular trading platforms include MetaTrader 4, cTrader, Multi Account Manager and more.",

    "demo_1": "Demo Trading Account Application",
    "demo_2": "- Free to open",
    "demo_3": "- Practice until you're ready to go live",
    "demo_4": "- All account types, platforms and products supported",
    "demo_5": "Live Trading Account",
    "demo_6": "Demo Account",
    "demo_7": "How to Deposit",
    "demo_8": "How to Withdraw",
    "demo_9": "Start trading with",
    "demo_10": "world’s largest True ECN forex broker",
    "demo_11": "Open Trading Account",
    "demo_12": "Try  a free demo"
}
